[
  {
    "album": "原神-闪耀的群星6 The Stellar Moments Vol. 6",
    "date": "2026-01-16",
    "tracks": [
      {
        "track": "环佩琳琅 Chiming Jade",
        "作曲 Composer": "路南 Lunan (HOYO-MiX)",
        "编曲 Arranger": "路南 Lunan (HOYO-MiX)",
        "制谱 Music Copyist": "殷照晴 Judy Yin (HOYO-MiX)",
        "乐队 Orchestra": "国际首席爱乐乐团 International Master Philharmonic Orchestra",
        "竹笛 Dizi": "丁晓逵 Xiaokui Ding",
        "箫 Xiao": "丁晓逵 Xiaokui Ding",
        "葫芦丝 Hulusi": "丁晓逵 Xiaokui Ding",
        "琵琶 Pipa": "刘小菁 Xiaojing Liu",
        "录音棚 Recording Studio": "九紫天诚录音棚 SKY FIRE STUDIO",
        "录音师 Recording Engineer": "董方昱 Fangyu Dong/陈鑫光 Xinguang Chen",
        "混音师 Mixing Engineer": "鸦雀有声 Anzol",
        "母带制作 Mastering Engineer": "鸦雀有声 Anzol",
        "出品 Produced by": "HOYO-MiX"
      },
      {
        "track": "梦的彼方 In Your Vision, or in None",
        "作曲 Composer": "陈子敏 Arcangelo Chen (HOYO-MiX)",
        "编曲 Arranger": "陈子敏 Arcangelo Chen (HOYO-MiX) /路南 Lunan (HOYO-MiX)",
        "制谱 Music Copyist": "月岛 TKSM (HOYO-MiX)",
        "乐队 Orchestra": "Budapest Scoring Orchestra/国际首席爱乐乐团 International Master Philharmonic Orchestra",
        "录音棚 Recording Studio": "九紫天诚录音棚 SKY FIRE STUDIO/Lang Studio",
        "录音师 Recording Engineer": "黄浩 Hao Huang",
        "混音师 Mixing Engineer": "鸦雀有声 Anzol",
        "母带制作 Mastering Engineer": "鸦雀有声 Anzol",
        "出品 Produced by": "HOYO-MiX"
      },
      {
        "track": "九十八随眠观 Tales From the Ninety-Eight-Nights",
        "作曲 Composer": "赵鑫 Xin Zhao (HOYO-MiX)",
        "编曲 Arranger": "赵鑫 Xin Zhao (HOYO-MiX)",
        "制谱 Music Copyist": "殷照晴 Judy Yin (HOYO-MiX)",
        "乐队 Orchestra": "国际首席爱乐乐团 International Master Philharmonic Orchestra",
        "尺八 Shakuhachi": "丁晓逵 Xiaokui Ding",
        "手风琴 Accordion": "刘昭 Zhao Liu",
        "中音萨克斯 Alto Saxophone": "李世海 Shihai Li",
        "次中音萨克斯 Tenor Saxophone": "陈沙桐 Shatong Chen",
        "小号 Trumpet": "高翊鈞 Yi-Jiun Kao/姜逸都 Yidu Jiang",
        "长号 Trombone": "曹侃 Kan Cao",
        "录音棚 Recording Studio": "九紫天诚录音棚 SKY FIRE STUDIO/Largo Studio",
        "录音师 Recording Engineer": "黄浩 Hao Huang/文扬 Witzar Young/黄建雄 Stephen",
        "混音师 Mixing Engineer": "黄巍 Zach Huang",
        "母带制作 Mastering Engineer": "鸦雀有声 Anzol",
        "出品 Produced by": "HOYO-MiX"
      },
      {
        "track": "健体之诲 Fitness Lesson",
        "作曲 Composer": "赵鑫 Xin Zhao (HOYO-MiX)",
        "编曲 Arranger": "赵鑫 Xin Zhao (HOYO-MiX)",
        "电吉他 Electric Guitar": "赵鑫 Xin Zhao (HOYO-MiX)",
        "混音师 Mixing Engineer": "鸦雀有声 Anzol",
        "母带制作 Mastering Engineer": "鸦雀有声 Anzol",
        "出品 Produced by": "HOYO-MiX"
      },
      {
        "track": "勇气的飨宴 The Feast of Valor",
        "作曲 Composer": "冯琳尧 Linyao Feng (HOYO-MiX)",
        "编曲 Arranger": "冯琳尧 Linyao Feng (HOYO-MiX)",
        "制谱 Music Copyist": "殷照晴 Judy Yin (HOYO-MiX)",
        "乐队 Orchestra": "国际首席爱乐乐团 International Master Philharmonic Orchestra",
        "电吉他 Electric Guitar": "陈磊（梦潼文化） Lei Chen (Dream Tone Studio)",
        "萨克斯 Saxophone": "富宇 Yu Fu",
        "录音棚 Recording Studio": "九紫天诚录音棚 SKY FIRE STUDIO",
        "录音师 Recording Engineer": "黄浩 Hao Huang",
        "混音师 Mixing Engineer": "鸦雀有声 Anzol",
        "母带制作 Mastering Engineer": "鸦雀有声 Anzol",
        "出品 Produced by": "HOYO-MiX"
      },
      {
        "track": "飒勇的豪斗 Valiant Duel",
        "作曲 Composer": "姜以君 Yijun Jiang (HOYO-MiX)",
        "编曲 Arranger": "姜以君 Yijun Jiang (HOYO-MiX)",
        "制谱 Music Copyist": "殷照晴 Judy Yin (HOYO-MiX)",
        "乐队 Orchestra": "国际首席爱乐乐团 International Master Philharmonic Orchestra",
        "黑嗓 Death Growl": "张江楠 Jiangnan Zhang",
        "人声 Voice": "开心蛙蛙 Kaixin Wawa",
        "电吉他 Electric Guitar": "姜以君 Yijun Jiang (HOYO-MiX)",
        "童声合唱指挥 Children's Choir Conductor": "李烨琳 Yelin Li",
        "童声合唱 Children's Choir": "深空合唱团 Deep Space Choir",
        "录音棚 Recording Studio": "九紫天诚录音棚 SKY FIRE STUDIO",
        "录音师 Recording Engineer": "董方昱 Fangyu Dong/阮泽霖 Raven",
        "混音师 Mixing Engineer": "鸦雀有声 Anzol",
        "母带制作 Mastering Engineer": "鸦雀有声 Anzol",
        "出品 Produced by": "HOYO-MiX"
      },
      {
        "track": "祛疾的清风 Healing Breeze",
        "作曲 Composer": "赵鑫 Xin Zhao (HOYO-MiX)",
        "编曲 Arranger": "赵鑫 Xin Zhao (HOYO-MiX)",
        "制谱 Music Copyist": "殷照晴 Judy Yin (HOYO-MiX)",
        "乐队 Orchestra": "国际首席爱乐乐团 International Master Philharmonic Orchestra",
        "共鸣器吉他 Resonator Guitar": "陈磊（梦潼文化） Lei Chen (Dream Tone Studio)",
        "录音棚 Recording Studio": "九紫天诚录音棚 SKY FIRE STUDIO",
        "录音师 Recording Engineer": "岳艮 Gen Yue",
        "混音师 Mixing Engineer": "鸦雀有声 Anzol",
        "母带制作 Mastering Engineer": "鸦雀有声 Anzol",
        "出品 Produced by": "HOYO-MiX"
      },
      {
        "track": "蛋糕上的樱桃 La cerise sur le gateau",
        "作曲 Composer": "尤裴佳 Peijia You (HOYO-MiX)",
        "编曲 Arranger": "尤裴佳 Peijia You (HOYO-MiX)",
        "制谱 Music Copyist": "殷照晴 Judy Yin (HOYO-MiX)",
        "乐队 Orchestra": "国际首席爱乐乐团 International Master Philharmonic Orchestra",
        "电吉他 Electric Guitar": "尤裴佳 Peijia You (HOYO-MiX)",
        "小提琴 Violin": "张琴 Qin Zhang",
        "录音棚 Recording Studio": "九紫天诚录音棚 SKY FIRE STUDIO",
        "录音师 Recording Engineer": "陈鑫光 Xinguang Chen/董方昱 Fangyu Dong",
        "混音师 Mixing Engineer": "鸦雀有声 Anzol",
        "母带制作 Mastering Engineer": "鸦雀有声 Anzol",
        "出品 Produced by": "HOYO-MiX"
      },
      {
        "track": "五味交响 La complexe symphonie en cuisine",
        "作曲 Composer": "尤裴佳 Peijia You (HOYO-MiX)",
        "编曲 Arranger": "尤裴佳 Peijia You (HOYO-MiX)",
        "制谱 Music Copyist": "彭龙飞 Landon Peng (HOYO-MiX)",
        "乐队 Orchestra": "国际首席爱乐乐团 International Master Philharmonic Orchestra",
        "手风琴 Accordion": "许笑男 Xiaonan Xu",
        "电吉他 Electric Guitar": "尤裴佳 Peijia You (HOYO-MiX)",
        "原声吉他 Acoustic Guitar": "尤裴佳 Peijia You (HOYO-MiX)",
        "小提琴 Violin": "刘睿 Rui Liu",
        "大提琴 Cello": "郎莹 Ying Lang",
        "录音棚 Recording Studio": "九紫天诚录音棚 SKY FIRE STUDIO",
        "录音师 Recording Engineer": "李鸿彦升 Hongyansheng Li/黄浩 Hao Huang",
        "混音师 Mixing Engineer": "鸦雀有声 Anzol",
        "母带制作 Mastering Engineer": "鸦雀有声 Anzol",
        "出品 Produced by": "HOYO-MiX"
      },
      {
        "track": "风拂水留痕 The Wind-Woven Poem Upon the Waters",
        "作曲 Composer": "冯琳尧 Linyao Feng (HOYO-MiX)",
        "编曲 Arranger": "冯琳尧 Linyao Feng (HOYO-MiX) /赵鑫 Xin Zhao (HOYO-MiX)",
        "制谱 Music Copyist": "彭龙飞 Landon Peng (HOYO-MiX)",
        "电吉他 Electric Guitar": "陈磊（梦潼文化） Lei Chen (Dream Tone Studio)",
        "混音师 Mixing Engineer": "鸦雀有声 Anzol",
        "母带制作 Mastering Engineer": "鸦雀有声 Anzol",
        "出品 Produced by": "HOYO-MiX"
      },
      {
        "track": "死生的终点 Where the Current Flows into Eternity",
        "作曲 Composer": "李洋 Yang Lee (HOYO-MiX)",
        "编曲 Arranger": "赵鑫 Xin Zhao (HOYO-MiX)",
        "制谱 Music Copyist": "高欢 Ghuan. (HOYO-MiX)",
        "民谣吉他 Acoustic Guitar": "陈磊（梦潼文化） Lei Chen (Dream Tone Studio)",
        "混音师 Mixing Engineer": "鸦雀有声 Anzol",
        "母带制作 Mastering Engineer": "鸦雀有声 Anzol",
        "出品 Produced by": "HOYO-MiX"
      },
      {
        "track": "亘古的极星 A Star to Every Wandering Bark",
        "作词 Lyricist": "项柳 Hsiang Liu",
        "作曲 Composer": "赵鑫 Xin Zhao (HOYO-MiX)",
        "编曲 Arranger": "赵鑫 Xin Zhao (HOYO-MiX)",
        "制谱 Music Copyist": "彭龙飞 Landon Peng (HOYO-MiX)",
        "乐队 Orchestra": "国际首席爱乐乐团 International Master Philharmonic Orchestra",
        "人声 Voice": "陈乐一 Loger",
        "电吉他 Electric Guitar": "赵鑫 Xin Zhao (HOYO-MiX)",
        "录音棚 Recording Studio": "九紫天诚录音棚 SKY FIRE STUDIO / Studio 21A",
        "录音师 Recording Engineer": "黄浩 Hao Huang / 多斯 Aydos (Studio 21A)",
        "混音师 Mixing Engineer": "鸦雀有声 Anzol",
        "母带制作 Mastering Engineer": "鸦雀有声 Anzol",
        "出品 Produced by": "HOYO-MiX"
      },
      {
        "track": "霓夜连踡 Ceaseless Banquet",
        "作曲 Composer": "罗静怡 Caroline Luo (HOYO-MiX)",
        "编曲 Arranger": "罗静怡 Caroline Luo (HOYO-MiX)",
        "制谱 Music Copyist": "周千朔 Qianshuo Zhou (HOYO-MiX)",
        "乐队 Orchestra": "国际首席爱乐乐团 International Master Philharmonic Orchestra",
        "尤克里里 Ukulele": "陈磊（梦潼文化） Lei Chen (Dream Tone Studio)",
        "电吉他 Electric Guitar": "陈磊（梦潼文化） Lei Chen (Dream Tone Studio)",
        "钢棒吉他 Lap Steel": "陈磊（梦潼文化） Lei Chen (Dream Tone Studio)",
        "录音棚 Recording Studio": "九紫天诚录音棚 SKY FIRE STUDIO",
        "录音师 Recording Engineer": "黄浩 Hao Huang",
        "混音师 Mixing Engineer": "鸦雀有声 Anzol",
        "母带制作 Mastering Engineer": "鸦雀有声 Anzol",
        "出品 Produced by": "HOYO-MiX"
      },
      {
        "track": "陋巷间的乐园 The Way to Elysium",
        "作曲 Composer": "李洋 Yang Lee (HOYO-MiX)",
        "编曲 Arranger": "陈子敏 Arcangelo Chen (HOYO-MiX)",
        "制谱 Music Copyist": "苏宸来 Chenlai Su/柯江 Jiang Ke (HOYO-MiX)",
        "乐队 Orchestra": "Budapest Scoring Orchestra",
        "爱尔兰风笛 Uilleann Pipes": "Philippe Barnes",
        "哨笛 Tin Whistle": "Philippe Barnes",
        "录音棚 Recording Studio": "Budapest Scoring",
        "录音师 Recording Engineer": "Viktor Szabó",
        "混音师 Mixing Engineer": "鸦雀有声 Anzol",
        "母带制作 Mastering Engineer": "鸦雀有声 Anzol",
        "出品 Produced by": "HOYO-MiX"
      },
      {
        "track": "明晨，明晨 Goodbye, or Another Tomorrow of Chue'q Chik",
        "作曲 Composer": "路南 Lunan (HOYO-MiX)",
        "编曲 Arranger": "路南 Lunan (HOYO-MiX)",
        "制谱 Music Copyist": "彭龙飞 Landon Peng (HOYO-MiX)",
        "乐队 Orchestra": "国际首席爱乐乐团 International Master Philharmonic Orchestra",
        "录音棚 Recording Studio": "九紫天诚录音棚 SKY FIRE STUDIO",
        "录音师 Recording Engineer": "黄浩 Hao Huang",
        "混音师 Mixing Engineer": "鸦雀有声 Anzol",
        "母带制作 Mastering Engineer": "鸦雀有声 Anzol",
        "出品 Produced by": "HOYO-MiX"
      },
      {
        "track": "山椒与梭鱼之战 War With Pepper and Fish",
        "作曲 Composer": "路南 Lunan (HOYO-MiX)",
        "编曲 Arranger": "路南 Lunan (HOYO-MiX)",
        "混音师 Mixing Engineer": "鸦雀有声 Anzol",
        "母带制作 Mastering Engineer": "鸦雀有声 Anzol",
        "出品 Produced by": "HOYO-MiX"
      },
      {
        "track": "巧思暇逸 Ingenious Trip",
        "作曲 Composer": "罗静怡 Caroline Luo (HOYO-MiX)",
        "编曲 Arranger": "罗静怡 Caroline Luo (HOYO-MiX)",
        "制谱 Music Copyist": "彭龙飞 Landon Peng (HOYO-MiX)",
        "乐队 Orchestra": "国际首席爱乐乐团 International Master Philharmonic Orchestra",
        "民谣吉他 Acoustic Guitar": "陈磊（梦潼文化） Lei Chen (Dream Tone Studio)",
        "电吉他 Electric Guitar": "陈磊（梦潼文化） Lei Chen (Dream Tone Studio)",
        "录音棚 Recording Studio": "九紫天诚录音棚 SKY FIRE STUDIO",
        "录音师 Recording Engineer": "黄浩 Hao Huang",
        "混音师 Mixing Engineer": "鸦雀有声 Anzol",
        "母带制作 Mastering Engineer": "鸦雀有声 Anzol",
        "出品 Produced by": "HOYO-MiX"
      },
      {
        "track": "若月尚未升起 Del Nepatekejusio Menulio",
        "作曲 Composer": "王予曦 Yuxi Wang (HOYO-MiX)",
        "编曲 Arranger": "王予曦 Yuxi Wang (HOYO-MiX)",
        "制谱 Music Copyist": "柯江 Jiang Ke (HOYO-MiX)",
        "乐队 Orchestra": "国际首席爱乐乐团 International Master Philharmonic Orchestra",
        "爱尔兰长笛 Irish Flute": "丁晓逵 Xiaokui Ding",
        "录音棚 Recording Studio": "九紫天诚录音棚 SKY FIRE STUDIO",
        "录音师 Recording Engineer": "黄浩 Hao Huang",
        "混音师 Mixing Engineer": "鸦雀有声 Anzol",
        "母带制作 Mastering Engineer": "鸦雀有声 Anzol",
        "出品 Produced by": "HOYO-MiX"
      },
      {
        "track": "银雪与圣林的回舞 Lumipyhaemetsaen Polkka",
        "作词 Lyricist": "项柳 Hsiang Liu",
        "作曲 Composer": "王予曦 Yuxi Wang (HOYO-MiX)",
        "编曲 Arranger": "王予曦 Yuxi Wang (HOYO-MiX)",
        "制谱 Music Copyist": "彭龙飞 Landon Peng (HOYO-MiX)",
        "乐队 Orchestra": "Budapest Scoring Orchestra",
        "人声 Voice": "Imogen Parry (London Voices)",
        "哨笛 Tin Whistle": "Philippe Barnes",
        "康特勒琴 Kantele": "Ida Elina",
        "合唱指挥 Choir Conductor": "Ben Parry",
        "合唱 Choir": "London Voices",
        "录音棚 Recording Studio": "Budapest Scoring / Air-Edel Recording Studios",
        "录音师 Recording Engineer": "Viktor Szabó / Olly Thompson",
        "混音师 Mixing Engineer": "鸦雀有声 Anzol",
        "母带制作 Mastering Engineer": "鸦雀有声 Anzol",
        "出品 Produced by": "HOYO-MiX"
      },
      {
        "track": "夤夜秘话 Anekdota en Nyktí"
      },
      {
        "track": "逝往苍焰 Entombed in Pale Fire",
        "作曲 Composer": "路南 Lunan (HOYO-MiX)",
        "编曲 Arranger": "路南 Lunan (HOYO-MiX)",
        "制谱 Music Copyist": "彭龙飞 Landon Peng (HOYO-MiX)",
        "乐队 Orchestra": "国际首席爱乐乐团 International Master Philharmonic Orchestra",
        "小提琴 Violin": "张琴 Qin Zhang",
        "录音棚 Recording Studio": "九紫天诚录音棚 SKY FIRE STUDIO",
        "录音师 Recording Engineer": "黄浩 Hao Huang/付钰 Yu Fu",
        "混音师 Mixing Engineer": "鸦雀有声 Anzol",
        "母带制作 Mastering Engineer": "鸦雀有声 Anzol",
        "出品 Produced by": "HOYO-MiX"
      },
      {
        "track": "织秘之觅 Sewing Sacred Secrets",
        "作曲 Composer": "赵鑫 Xin Zhao (HOYO-MiX)",
        "编曲 Arranger": "赵鑫 Xin Zhao (HOYO-MiX)",
        "制谱 Music Copyist": "周千朔 Qianshuo Zhou (HOYO-MiX)",
        "乐队 Orchestra": "国际首席爱乐乐团 International Master Philharmonic Orchestra",
        "录音棚 Recording Studio": "九紫天诚录音棚 SKY FIRE STUDIO",
        "录音师 Recording Engineer": "岳艮 Gen Yue/黄浩 Hao Huang",
        "混音师 Mixing Engineer": "鸦雀有声 Anzol",
        "母带制作 Mastering Engineer": "鸦雀有声 Anzol",
        "出品 Produced by": "HOYO-MiX"
      },
      {
        "track": "热砂的倦戏 Machination of Mehenet",
        "作词 Lyricist": "项柳 Hsiang Liu",
        "作曲 Composer": "路南 Lunan (HOYO-MiX)",
        "编曲 Arranger": "路南 Lunan (HOYO-MiX)",
        "演唱 Artist": "宗祈辰 Jessie",
        "录音棚 Recording Studio": "Manhattan Beach Recording",
        "录音师 Recording Engineer": "Mason Lee",
        "混音师 Mixing Engineer": "鸦雀有声 Anzol",
        "母带制作 Mastering Engineer": "鸦雀有声 Anzol",
        "出品 Produced by": "HOYO-MiX"
      },
      {
        "track": "互助方案！ For Your Cash Only",
        "作曲 Composer": "索德尔 Deer Suo (HOYO-MiX)",
        "编曲 Arranger": "索德尔 Deer Suo (HOYO-MiX)",
        "制谱 Music Copyist": "高欢 Ghuan. (HOYO-MiX)",
        "乐队 Orchestra": "Budapest Scoring Orchestra",
        "电吉他 Electric Guitar": "陈磊（梦潼文化） Lei Chen (Dream Tone Studio)",
        "录音棚 Recording Studio": "Budapest Scoring",
        "录音师 Recording Engineer": "Viktor Szabó",
        "混音师 Mixing Engineer": "鸦雀有声 Anzol",
        "母带制作 Mastering Engineer": "鸦雀有声 Anzol",
        "出品 Produced by": "HOYO-MiX"
      },
      {
        "track": "未尽的心语 Unwritten Stories",
        "作曲 Composer": "陈子敏 Arcangelo Chen (HOYO-MiX)",
        "编曲 Arranger": "陈子敏 Arcangelo Chen (HOYO-MiX)",
        "制谱 Music Copyist": "彭龙飞 Landon Peng (HOYO-MiX)",
        "乐队 Orchestra": "Budapest Scoring Orchestra",
        "古典吉他 Classical Guitar": "陈磊（梦潼文化） Lei Chen (Dream Tone Studio)",
        "录音棚 Recording Studio": "Budapest Scoring",
        "录音师 Recording Engineer": "Viktor Szabó",
        "混音师 Mixing Engineer": "鸦雀有声 Anzol",
        "母带制作 Mastering Engineer": "鸦雀有声 Anzol",
        "出品 Produced by": "HOYO-MiX"
      },
      {
        "track": "完遂的美梦 Summa Perfectionis",
        "作曲 Composer": "赵鑫 Xin Zhao (HOYO-MiX)",
        "编曲 Arranger": "赵鑫 Xin Zhao (HOYO-MiX)",
        "制谱 Music Copyist": "周千朔 Qianshuo Zhou (HOYO-MiX)",
        "乐队 Orchestra": "国际首席爱乐乐团 International Master Philharmonic Orchestra",
        "小提琴 Violin": "张琴 Qin Zhang",
        "录音棚 Recording Studio": "九紫天诚录音棚 SKY FIRE STUDIO",
        "录音师 Recording Engineer": "黄浩 Hao Huang",
        "混音师 Mixing Engineer": "鸦雀有声 Anzol",
        "母带制作 Mastering Engineer": "鸦雀有声 Anzol",
        "出品 Produced by": "HOYO-MiX"
      },
      {
        "track": "晴云似絮 Soft as Willow Down",
        "作曲 Composer": "路南 Lunan (HOYO-MiX)",
        "编曲 Arranger": "路南 Lunan (HOYO-MiX)",
        "制谱 Music Copyist": "柯江 Jiang Ke (HOYO-MiX)",
        "竹笛 Dizi": "丁晓逵 Xiaokui Ding",
        "箫 Xiao": "丁晓逵 Xiaokui Ding",
        "琵琶 Pipa": "孙莹 Ying Sun",
        "小提琴 Violin": "张琴 Qin Zhang",
        "录音棚 Recording Studio": "Ready Steady Sound!",
        "录音师 Recording Engineer": "日生 Sheng Ri",
        "混音师 Mixing Engineer": "鸦雀有声 Anzol",
        "母带制作 Mastering Engineer": "鸦雀有声 Anzol",
        "出品 Produced by": "HOYO-MiX"
      },
      {
        "track": "终宴不知疲 We Shall Sing All Night",
        "作曲 Composer": "李洋 Yang Lee (HOYO-MiX)",
        "编曲 Arranger": "李洋 Yang Lee (HOYO-MiX)",
        "制谱 Music Copyist": "周千朔 Qianshuo Zhou (HOYO-MiX)",
        "乐队 Orchestra": "Budapest Scoring Orchestra",
        "人声 Voice": "亦乐 Elim",
        "录音棚 Recording Studio": "Budapest Scoring",
        "录音师 Recording Engineer": "Viktor Szabó",
        "混音师 Mixing Engineer": "黄巍 Zach Huang",
        "母带制作 Mastering Engineer": "鸦雀有声 Anzol",
        "出品 Produced by": "HOYO-MiX"
      },
      {
        "track": "别夜寻月 Catching the Glow",
        "作曲 Composer": "李洋 Yang Lee (HOYO-MiX)",
        "编曲 Arranger": "李洋 Yang Lee (HOYO-MiX)",
        "制谱 Music Copyist": "彭龙飞 Landon Peng (HOYO-MiX)",
        "乐队 Orchestra": "国际首席爱乐乐团 International Master Philharmonic Orchestra",
        "大提琴 Cello": "陈小龙 Xiaolong Chen",
        "合唱 Choir": "Genshin Choir",
        "录音棚 Recording Studio": "Ready Steady Sound! /佳荧录音棚 Chirying Studio",
        "录音师 Recording Engineer": "日生 Sheng Ri/莫家伟 Jiawei Mo",
        "混音师 Mixing Engineer": "黄巍 Zach Huang",
        "母带制作 Mastering Engineer": "鸦雀有声 Anzol",
        "出品 Produced by": "HOYO-MiX"
      },
      {
        "track": "献向镜水的月光 Song to the Mirrored Moon",
        "作曲 Composer": "李洋 Yang Lee (HOYO-MiX)",
        "编曲 Arranger": "李洋 Yang Lee (HOYO-MiX)",
        "制谱 Music Copyist": "柯江 Jiang Ke (HOYO-MiX)",
        "乐队 Orchestra": "Budapest Scoring Orchestra/国际首席爱乐乐团 International Master Philharmonic Orchestra",
        "演唱 Vocal Artist": "真栗 Makuri",
        "第一小提琴 First Violin": "朱玥 Yue Zhu",
        "第二小提琴 Second Violin": "张羽僮 Yutong Zhang",
        "第一中提琴 First Viola": "俞海峰 Haifeng Yu",
        "第二中提琴 Second Viola": "茅异竹 Yizhu Mao",
        "大提琴 Cello": "陈小龙 Xiaolong Chen",
        "低音提琴 Double Bass": "杨冰洋 Bingyang Yang",
        "哥伦比娅清唱 Columbina's Voice": "亦乐 Elim",
        "合唱 Choir": "Budapest Scoring Choir",
        "录音棚 Recording Studio": "Budapest Scoring/九紫天诚录音棚 SKY FIRE STUDIO / 52Hz Studio/佳荧录音棚 Chirying Studio",
        "录音师 Recording Engineer": "Viktor Szabó/黄浩 Hao Huang/潘俊宇 Ausar Pan (52Hz Studio) /莫家伟 Jiawei Mo",
        "混音师 Mixing Engineer": "鸦雀有声 Anzol",
        "母带制作 Mastering Engineer": "鸦雀有声 Anzol",
        "出品 Produced by": "HOYO-MiX"
      }
    ]
  }
]